cbstorage/__init__.py
cbstorage/storage.py
cbstorage-0.1.6.dist-info/WHEEL
cbstorage-0.1.6.dist-info/METADATA
cbstorage-0.1.6.dist-info/RECORD
